whereisip/__init__.py
whereisip/getgeolocation.py
whereisip/utils.py
whereisip-1.2.7.dist-info/LICENSE.txt
whereisip-1.2.7.dist-info/METADATA
whereisip-1.2.7.dist-info/WHEEL
whereisip-1.2.7.dist-info/entry_points.txt
whereisip-1.2.7.dist-info/top_level.txt
whereisip-1.2.7.dist-info/RECORD
