Metadata-Version: 2.1
Name: whereisip
Version: 1.2.7
Summary: Get the geolocation of the current server
Home-page: https://github.com/pyscaffold/pyscaffold/
Author: Eelco van Vliet
Author-email: eelcovv@gmail.com
License: MIT
Project-URL: Documentation, http://whereisip.readthedocs.io/
Project-URL: Source, https://github.com/eelcovv/whereisip
Project-URL: Changelog, https://whereisip.readthedocs.io/en/latest/changelog.html
Project-URL: Download, https://pypi.org/project/whereisip/#files
Platform: any
Classifier: Development Status :: 4 - Beta
Classifier: Programming Language :: Python
License-File: LICENSE.txt
Requires-Dist: appdirs
Requires-Dist: country-converter
Requires-Dist: geocoder
Requires-Dist: latloncalc
Requires-Dist: importlib-metadata ; python_version < "3.8"
Provides-Extra: testing
Requires-Dist: setuptools ; extra == 'testing'
Requires-Dist: pytest ; extra == 'testing'
Requires-Dist: pytest-cov ; extra == 'testing'
